spamir_updater/__init__.py
spamir_updater/encryption.py
spamir_updater/network.py
spamir_updater/self_updater.py
spamir_updater/updater_client.py
spamir_updater/utils.py
spamir_updater-2.0.0.dist-info/LICENSE
spamir_updater-2.0.0.dist-info/METADATA
spamir_updater-2.0.0.dist-info/WHEEL
spamir_updater-2.0.0.dist-info/top_level.txt
spamir_updater-2.0.0.dist-info/RECORD
