Metadata-Version: 2.1
Name: spamir-updater
Version: 2.0.0
Summary: Secure automatic update client for Python applications
Home-page: https://github.com/spamir/spamir-updater
Author: Spamir
Author-email: spamirorg@proton.me
License: UNKNOWN
Platform: UNKNOWN
Classifier: Development Status :: 5 - Production/Stable
Classifier: Intended Audience :: Developers
Classifier: License :: OSI Approved :: MIT License
Classifier: Operating System :: OS Independent
Classifier: Programming Language :: Python :: 3
Classifier: Programming Language :: Python :: 3.7
Classifier: Programming Language :: Python :: 3.8
Classifier: Programming Language :: Python :: 3.9
Classifier: Programming Language :: Python :: 3.10
Classifier: Programming Language :: Python :: 3.11
Classifier: Programming Language :: Python :: 3.12
Classifier: Topic :: Software Development :: Libraries :: Python Modules
Classifier: Topic :: System :: Software Distribution
Requires-Python: >=3.7
License-File: LICENSE
Requires-Dist: cryptography (>=38.0.0)
Requires-Dist: packaging (>=21.0)
Requires-Dist: psutil (>=5.8.0)
Requires-Dist: requests (>=2.28.0)
Requires-Dist: importlib-metadata (>=1.0) ; python_version < "3.8"
